forest_visualizer/__init__.py
forest_visualizer/forest.py
forest_visualization-0.1.3.dist-info/LICENSE
forest_visualization-0.1.3.dist-info/METADATA
forest_visualization-0.1.3.dist-info/WHEEL
forest_visualization-0.1.3.dist-info/top_level.txt
forest_visualization-0.1.3.dist-info/RECORD
