Metadata-Version: 2.1
Name: forest-visualization
Version: 0.1.3
Summary: A Python package for forest structure visualization and traversals
Home-page: https://github.com/ganeshb15/forest-visualization
Author: Ganesh Bhagwat,Shristi Kumari,Vaishnavi Patekar
Author-email: bhagwatganesh716@gmail.com
License: UNKNOWN
Platform: UNKNOWN
Classifier: Programming Language :: Python :: 3
Classifier: License :: OSI Approved :: MIT License
Classifier: Operating System :: OS Independent
Requires-Python: >=3.6
License-File: LICENSE
Requires-Dist: Pillow
